{
  "courses": [
    {
      "courseId": "C148",
      "courseTitle": "Programming 1",
      "courseDescription": "mafesh",
      "instructorId": "1",
      "lessons": [
        {
          "lessonId": "L185",
          "lessonTitle": "OOP",
          "content": "mafesh",
          "resources": [
            "mafesh"
          ],
          "status": true,
          "quiz": {
            "quizId": "QZ2175",
            "questions": [
              {
                "questionBody": "Who is the shortest?",
                "choices": [
                  "Heba",
                  "Roaa",
                  "Habiba",
                  "Darine"
                ],
                "answer": "B"
              }
            ],
            "passingScore": 50.0,
            "maxAttempts": 5
          },
          "quizstate": false,
          "quizPassed": false
        },
        {
          "lessonId": "L165",
          "lessonTitle": "UML",
          "content": "mafesh",
          "resources": [
            "mafesh"
          ],
          "status": true,
          "quiz": {
            "quizId": "QZ3079",
            "questions": [
              {
                "questionBody": "Darine\u0027s cat name?",
                "choices": [
                  "Jullitee",
                  "Romio",
                  "Loly",
                  "Bobo"
                ],
                "answer": "B"
              },
              {
                "questionBody": "My name is",
                "choices": [
                  "Hebo",
                  "HuaLing",
                  "HuaHua",
                  "All of the above"
                ],
                "answer": "D"
              }
            ],
            "passingScore": 50.0,
            "maxAttempts": 5
          },
          "quizstate": false,
          "quizPassed": false
        },
        {
          "lessonId": "L183",
          "lessonTitle": "Design",
          "content": "mafesh",
          "resources": [
            "mafesh"
          ],
          "status": true,
          "quiz": {
            "quizId": "QZ1355",
            "questions": [
              {
                "questionBody": "Men 5d best player in Africa this year?",
                "choices": [
                  "Marmoush",
                  "Salah",
                  "Hakemi",
                  "Me7rz"
                ],
                "answer": "C"
              }
            ],
            "passingScore": 50.0,
            "maxAttempts": 5
          },
          "quizstate": false,
          "quizPassed": false
        }
      ],
      "studentIds": [],
      "status": "Approved"
    }
  ]
}